agent/log_agent.c
libipc/shared_buffer.c
libipc/shared_buffer.h
ming_drlms/__init__.py
ming_drlms/_version.py
ming_drlms/config.py
ming_drlms/i18n.py
ming_drlms/main.py
ming_drlms/state.py
ming_drlms/update_check.py
ming_drlms/users.py
ming_drlms/bin/ipc_sender
ming_drlms/bin/libipc.so
ming_drlms/bin/log_collector_server
ming_drlms/bin/log_consumer
ming_drlms/bin/proc_launcher
ming_drlms/cli/__init__.py
ming_drlms/cli/client.py
ming_drlms/cli/config.py
ming_drlms/cli/demo.py
ming_drlms/cli/help.py
ming_drlms/cli/ipc.py
ming_drlms/cli/room.py
ming_drlms/cli/server.py
ming_drlms/cli/space.py
ming_drlms/cli/user.py
ming_drlms/cli/utils.py
ming_drlms/cli/dev/__init__.py
ming_drlms/cli/dev/artifacts.py
ming_drlms/cli/dev/coverage.py
ming_drlms/cli/dev/pkg.py
ming_drlms/cli/dev/test.py
ming_drlms/cli_help/client.md
ming_drlms/cli_help/dev.md
ming_drlms/cli_help/ipc.md
ming_drlms/cli_help/room.md
ming_drlms/cli_help/server.md
ming_drlms/cli_help/space.md
ming_drlms/cli_help/user.md
ming_drlms-0.3.2.dist-info/licenses/LICENSE
server/log_collector_server.c
server/rooms.c
server/rooms.h
tools/ipc_sender.c
tools/log_consumer.c
tools/proc_launcher.c
ming_drlms-0.3.2.dist-info/METADATA
ming_drlms-0.3.2.dist-info/WHEEL
ming_drlms-0.3.2.dist-info/entry_points.txt
ming_drlms-0.3.2.dist-info/top_level.txt
ming_drlms-0.3.2.dist-info/RECORD
