Metadata-Version: 2.4
Name: ming-drlms
Version: 0.3.2
Summary: CLI wrapper for DRLMS server/agent with pretty UX
Author-email: lgnorant-lu <zhouzihan825@gmail.com>
License-Expression: MIT
Project-URL: Source, https://github.com/lgnorant-lu/ming-drlms
Classifier: Programming Language :: Python :: 3
Classifier: Operating System :: POSIX :: Linux
Requires-Python: >=3.8
License-File: LICENSE
Requires-Dist: typer[all]
Requires-Dist: pyyaml
Requires-Dist: rich
Requires-Dist: psutil
Requires-Dist: argon2-cffi
Requires-Dist: requests
Requires-Dist: packaging
Dynamic: license-file
